<?xml version="1.0" encoding="utf-8"?>
<clothing-items>
 <clothing>
  <id>
   506241160
  </id>
  <name>
   DC Gloves M-7413
  </name>
  <category>
   Gloves
  </category>
  <size>
   L
  </size>
  <color>
   Оранжевый
  </color>
  <material>
   Кожа
  </material>
  <price>
   737184
  </price>
  <rating>
   1.02
  </rating>
  <reviews>
   717173
  </reviews>
 </clothing>
 <clothing>
  <id>
   440943909
  </id>
  <name>
   Vans Jeans P-4214
  </name>
  <category>
   Jeans
  </category>
  <size>
   L
  </size>
  <color>
   Красный
  </color>
  <material>
   Нейлон
  </material>
  <price>
   146887
  </price>
  <rating>
   1.09
  </rating>
  <reviews>
   980916
  </reviews>
  <new>
   +
  </new>
  <exclusive>
   no
  </exclusive>
 </clothing>
 <clothing>
  <id>
   815580425
  </id>
  <name>
   Asics Shirt A-1088
  </name>
  <category>
   Shirt
  </category>
  <size>
   XXL
  </size>
  <color>
   Синий
  </color>
  <material>
   Лен
  </material>
  <price>
   870728
  </price>
  <rating>
   3.93
  </rating>
  <reviews>
   552426
  </reviews>
  <sporty>
   yes
  </sporty>
 </clothing>
 <clothing>
  <id>
   313739787
  </id>
  <name>
   Brooks Gloves Y-7296
  </name>
  <category>
   Gloves
  </category>
  <size>
   M
  </size>
  <color>
   Синий
  </color>
  <material>
   Шерсть
  </material>
  <price>
   100811
  </price>
  <rating>
   3.58
  </rating>
  <reviews>
   963354
  </reviews>
  <sporty>
   no
  </sporty>
 </clothing>
 <clothing>
  <id>
   285816269
  </id>
  <name>
   Nike Belts O-3183
  </name>
  <category>
   Belts
  </category>
  <size>
   L
  </size>
  <color>
   Фиолетовый
  </color>
  <material>
   Хлопок
  </material>
  <price>
   744546
  </price>
  <rating>
   2.87
  </rating>
  <reviews>
   732627
  </reviews>
  <new>
   -
  </new>
  <exclusive>
   no
  </exclusive>
 </clothing>
 <clothing>
  <id>
   930411257
  </id>
  <name>
   Ellesse Skirt O-9492
  </name>
  <category>
   Skirt
  </category>
  <size>
   XL
  </size>
  <color>
   Синий
  </color>
  <material>
   Шерсть
  </material>
  <price>
   855511
  </price>
  <rating>
   1.19
  </rating>
  <reviews>
   352759
  </reviews>
  <new>
   +
  </new>
  <exclusive>
   yes
  </exclusive>
 </clothing>
 <clothing>
  <id>
   856104795
  </id>
  <name>
   Adidas Skirt V-4136
  </name>
  <category>
   Skirt
  </category>
  <size>
   XXL
  </size>
  <color>
   Синий
  </color>
  <material>
   Полиэстер
  </material>
  <price>
   274707
  </price>
  <rating>
   2.9
  </rating>
  <reviews>
   21945
  </reviews>
  <new>
   -
  </new>
  <sporty>
   no
  </sporty>
 </clothing>
 <clothing>
  <id>
   220541296
  </id>
  <name>
   DC Dress L-3088
  </name>
  <category>
   Dress
  </category>
  <size>
   XL
  </size>
  <color>
   Голубой
  </color>
  <material>
   Кожа
  </material>
  <price>
   632150
  </price>
  <rating>
   3.04
  </rating>
  <reviews>
   531186
  </reviews>
  <exclusive>
   no
  </exclusive>
 </clothing>
 <clothing>
  <id>
   177294828
  </id>
  <name>
   Under Armour Belts H-7218
  </name>
  <category>
   Belts
  </category>
  <size>
   XXL
  </size>
  <color>
   Голубой
  </color>
  <material>
   Кожа
  </material>
  <price>
   711248
  </price>
  <rating>
   3.72
  </rating>
  <reviews>
   969985
  </reviews>
  <new>
   -
  </new>
  <exclusive>
   no
  </exclusive>
  <sporty>
   no
  </sporty>
 </clothing>
 <clothing>
  <id>
   328985776
  </id>
  <name>
   DC Skirt S-7813
  </name>
  <category>
   Skirt
  </category>
  <size>
   XL
  </size>
  <color>
   Фиолетовый
  </color>
  <material>
   Кожа
  </material>
  <price>
   466934
  </price>
  <rating>
   4.52
  </rating>
  <reviews>
   567721
  </reviews>
  <new>
   +
  </new>
  <exclusive>
   yes
  </exclusive>
 </clothing>
 <clothing>
  <id>
   214073280
  </id>
  <name>
   Addidas Jeans E-7850
  </name>
  <category>
   Jeans
  </category>
  <size>
   S
  </size>
  <color>
   Оранжевый
  </color>
  <material>
   Вискоза
  </material>
  <price>
   269806
  </price>
  <rating>
   1.81
  </rating>
  <reviews>
   502496
  </reviews>
  <new>
   -
  </new>
  <exclusive>
   no
  </exclusive>
 </clothing>
 <clothing>
  <id>
   956504148
  </id>
  <name>
   Adidas Hat H-9865
  </name>
  <category>
   Hat
  </category>
  <size>
   M
  </size>
  <color>
   Голубой
  </color>
  <material>
   Полиэстер
  </material>
  <price>
   512016
  </price>
  <rating>
   3.03
  </rating>
  <reviews>
   879454
  </reviews>
  <new>
   -
  </new>
 </clothing>
 <clothing>
  <id>
   672592113
  </id>
  <name>
   DC Umbrellas X-1691
  </name>
  <category>
   Umbrellas
  </category>
  <size>
   XL
  </size>
  <color>
   Голубой
  </color>
  <material>
   Полиэстер
  </material>
  <price>
   288429
  </price>
  <rating>
   1.63
  </rating>
  <reviews>
   655010
  </reviews>
 </clothing>
 <clothing>
  <id>
   937705753
  </id>
  <name>
   Under Armour Shoes I-9533
  </name>
  <category>
   Shoes
  </category>
  <size>
   M
  </size>
  <color>
   Красный
  </color>
  <material>
   Лен
  </material>
  <price>
   535688
  </price>
  <rating>
   1.11
  </rating>
  <reviews>
   977205
  </reviews>
  <sporty>
   yes
  </sporty>
 </clothing>
 <clothing>
  <id>
   794328375
  </id>
  <name>
   Converse Jeans R-6456
  </name>
  <category>
   Jeans
  </category>
  <size>
   S
  </size>
  <color>
   Синий
  </color>
  <material>
   Хлопок
  </material>
  <price>
   257569
  </price>
  <rating>
   2.61
  </rating>
  <reviews>
   880850
  </reviews>
  <new>
   -
  </new>
  <exclusive>
   no
  </exclusive>
  <sporty>
   no
  </sporty>
 </clothing>
 <clothing>
  <id>
   690478386
  </id>
  <name>
   Brooks Skirt G-6106
  </name>
  <category>
   Skirt
  </category>
  <size>
   XL
  </size>
  <color>
   Зеленый
  </color>
  <material>
   Шелк
  </material>
  <price>
   612866
  </price>
  <rating>
   1.14
  </rating>
  <reviews>
   802958
  </reviews>
  <new>
   +
  </new>
  <exclusive>
   no
  </exclusive>
 </clothing>
 <clothing>
  <id>
   723199841
  </id>
  <name>
   DC T-shirt X-2741
  </name>
  <category>
   T-shirt
  </category>
  <size>
   M
  </size>
  <color>
   Красный
  </color>
  <material>
   Полиэстер
  </material>
  <price>
   972428
  </price>
  <rating>
   4.19
  </rating>
  <reviews>
   8792
  </reviews>
  <exclusive>
   no
  </exclusive>
 </clothing>
 <clothing>
  <id>
   832027853
  </id>
  <name>
   Brooks Jeans R-3690
  </name>
  <category>
   Jeans
  </category>
  <size>
   S
  </size>
  <color>
   Синий
  </color>
  <material>
   Кожа
  </material>
  <price>
   503432
  </price>
  <rating>
   3.52
  </rating>
  <reviews>
   651720
  </reviews>
  <sporty>
   yes
  </sporty>
 </clothing>
 <clothing>
  <id>
   561290315
  </id>
  <name>
   Converse Shoes I-4275
  </name>
  <category>
   Shoes
  </category>
  <size>
   L
  </size>
  <color>
   Фиолетовый
  </color>
  <material>
   Полиэстер
  </material>
  <price>
   430675
  </price>
  <rating>
   4.9
  </rating>
  <reviews>
   691065
  </reviews>
  <exclusive>
   no
  </exclusive>
 </clothing>
 <clothing>
  <id>
   304949021
  </id>
  <name>
   PleinSport Sweater N-4082
  </name>
  <category>
   Sweater
  </category>
  <size>
   XL
  </size>
  <color>
   Желтый
  </color>
  <material>
   Шелк
  </material>
  <price>
   656840
  </price>
  <rating>
   4.54
  </rating>
  <reviews>
   938358
  </reviews>
  <new>
   -
  </new>
  <sporty>
   no
  </sporty>
 </clothing>
</clothing-items>
