<?xml version="1.0" encoding="utf-8"?>
<clothing-items>
 <clothing>
  <id>
   995033524
  </id>
  <name>
   Lacoste Skirt R-9772
  </name>
  <category>
   Skirt
  </category>
  <size>
   L
  </size>
  <color>
   Голубой
  </color>
  <material>
   Шелк
  </material>
  <price>
   167377
  </price>
  <rating>
   2.0
  </rating>
  <reviews>
   314787
  </reviews>
  <new>
   -
  </new>
  <sporty>
   no
  </sporty>
 </clothing>
 <clothing>
  <id>
   483552479
  </id>
  <name>
   PleinSport Socks V-2007
  </name>
  <category>
   Socks
  </category>
  <size>
   XXL
  </size>
  <color>
   Красный
  </color>
  <material>
   Хлопок
  </material>
  <price>
   749484
  </price>
  <rating>
   1.18
  </rating>
  <reviews>
   218991
  </reviews>
  <exclusive>
   no
  </exclusive>
  <sporty>
   no
  </sporty>
 </clothing>
 <clothing>
  <id>
   899914714
  </id>
  <name>
   Brooks Socks A-1105
  </name>
  <category>
   Socks
  </category>
  <size>
   XL
  </size>
  <color>
   Синий
  </color>
  <material>
   Шерсть
  </material>
  <price>
   156965
  </price>
  <rating>
   3.19
  </rating>
  <reviews>
   248830
  </reviews>
  <exclusive>
   no
  </exclusive>
 </clothing>
 <clothing>
  <id>
   598550153
  </id>
  <name>
   Brooks T-shirt L-3424
  </name>
  <category>
   T-shirt
  </category>
  <size>
   M
  </size>
  <color>
   Фиолетовый
  </color>
  <material>
   Полиэстер
  </material>
  <price>
   473237
  </price>
  <rating>
   2.27
  </rating>
  <reviews>
   574203
  </reviews>
  <sporty>
   yes
  </sporty>
 </clothing>
 <clothing>
  <id>
   935564406
  </id>
  <name>
   Adidas Umbrellas P-7598
  </name>
  <category>
   Umbrellas
  </category>
  <size>
   XXL
  </size>
  <color>
   Голубой
  </color>
  <material>
   Шерсть
  </material>
  <price>
   803255
  </price>
  <rating>
   4.34
  </rating>
  <reviews>
   524804
  </reviews>
  <new>
   -
  </new>
  <exclusive>
   yes
  </exclusive>
  <sporty>
   no
  </sporty>
 </clothing>
 <clothing>
  <id>
   131705081
  </id>
  <name>
   Adidas Shirt I-2992
  </name>
  <category>
   Shirt
  </category>
  <size>
   XXL
  </size>
  <color>
   Желтый
  </color>
  <material>
   Шерсть
  </material>
  <price>
   196066
  </price>
  <rating>
   1.09
  </rating>
  <reviews>
   455998
  </reviews>
  <sporty>
   no
  </sporty>
 </clothing>
 <clothing>
  <id>
   909350434
  </id>
  <name>
   Puma Skirt D-3594
  </name>
  <category>
   Skirt
  </category>
  <size>
   XXL
  </size>
  <color>
   Зеленый
  </color>
  <material>
   Хлопок
  </material>
  <price>
   701971
  </price>
  <rating>
   3.04
  </rating>
  <reviews>
   408332
  </reviews>
  <new>
   -
  </new>
  <sporty>
   no
  </sporty>
 </clothing>
 <clothing>
  <id>
   350017328
  </id>
  <name>
   Addidas Shoes W-8651
  </name>
  <category>
   Shoes
  </category>
  <size>
   XL
  </size>
  <color>
   Красный
  </color>
  <material>
   Нейлон
  </material>
  <price>
   667541
  </price>
  <rating>
   4.52
  </rating>
  <reviews>
   572560
  </reviews>
  <exclusive>
   no
  </exclusive>
  <sporty>
   no
  </sporty>
 </clothing>
 <clothing>
  <id>
   227747819
  </id>
  <name>
   Ellesse Dress D-4351
  </name>
  <category>
   Dress
  </category>
  <size>
   S
  </size>
  <color>
   Фиолетовый
  </color>
  <material>
   Лен
  </material>
  <price>
   564783
  </price>
  <rating>
   3.4
  </rating>
  <reviews>
   896488
  </reviews>
  <new>
   -
  </new>
  <exclusive>
   no
  </exclusive>
 </clothing>
 <clothing>
  <id>
   899172847
  </id>
  <name>
   New Balance Belts R-5830
  </name>
  <category>
   Belts
  </category>
  <size>
   S
  </size>
  <color>
   Желтый
  </color>
  <material>
   Кожа
  </material>
  <price>
   865655
  </price>
  <rating>
   3.8
  </rating>
  <reviews>
   685796
  </reviews>
  <new>
   -
  </new>
  <exclusive>
   no
  </exclusive>
 </clothing>
 <clothing>
  <id>
   550110905
  </id>
  <name>
   Converse Sweater L-1978
  </name>
  <category>
   Sweater
  </category>
  <size>
   S
  </size>
  <color>
   Голубой
  </color>
  <material>
   Нейлон
  </material>
  <price>
   802564
  </price>
  <rating>
   4.81
  </rating>
  <reviews>
   19099
  </reviews>
  <new>
   -
  </new>
  <exclusive>
   no
  </exclusive>
  <sporty>
   yes
  </sporty>
 </clothing>
 <clothing>
  <id>
   527040444
  </id>
  <name>
   Addidas Pants O-1696
  </name>
  <category>
   Pants
  </category>
  <size>
   XXL
  </size>
  <color>
   Желтый
  </color>
  <material>
   Полиэстер
  </material>
  <price>
   482664
  </price>
  <rating>
   2.7
  </rating>
  <reviews>
   716215
  </reviews>
  <exclusive>
   no
  </exclusive>
 </clothing>
 <clothing>
  <id>
   618428908
  </id>
  <name>
   Addidas Umbrellas X-7558
  </name>
  <category>
   Umbrellas
  </category>
  <size>
   XL
  </size>
  <color>
   Зеленый
  </color>
  <material>
   Шелк
  </material>
  <price>
   648008
  </price>
  <rating>
   2.86
  </rating>
  <reviews>
   698111
  </reviews>
  <new>
   +
  </new>
  <exclusive>
   no
  </exclusive>
  <sporty>
   no
  </sporty>
 </clothing>
 <clothing>
  <id>
   892561317
  </id>
  <name>
   Addidas Umbrellas T-1501
  </name>
  <category>
   Umbrellas
  </category>
  <size>
   L
  </size>
  <color>
   Синий
  </color>
  <material>
   Шелк
  </material>
  <price>
   523955
  </price>
  <rating>
   2.99
  </rating>
  <reviews>
   809121
  </reviews>
  <new>
   -
  </new>
  <sporty>
   yes
  </sporty>
 </clothing>
 <clothing>
  <id>
   302329718
  </id>
  <name>
   Fila Handbags V-9767
  </name>
  <category>
   Handbags
  </category>
  <size>
   L
  </size>
  <color>
   Желтый
  </color>
  <material>
   Лен
  </material>
  <price>
   280709
  </price>
  <rating>
   1.1
  </rating>
  <reviews>
   375043
  </reviews>
  <new>
   -
  </new>
  <exclusive>
   no
  </exclusive>
  <sporty>
   no
  </sporty>
 </clothing>
 <clothing>
  <id>
   210905442
  </id>
  <name>
   Converse Pants H-5065
  </name>
  <category>
   Pants
  </category>
  <size>
   M
  </size>
  <color>
   Оранжевый
  </color>
  <material>
   Кожа
  </material>
  <price>
   427985
  </price>
  <rating>
   3.93
  </rating>
  <reviews>
   889609
  </reviews>
  <exclusive>
   no
  </exclusive>
  <sporty>
   no
  </sporty>
 </clothing>
 <clothing>
  <id>
   480064132
  </id>
  <name>
   Nike Shirt D-4687
  </name>
  <category>
   Shirt
  </category>
  <size>
   L
  </size>
  <color>
   Фиолетовый
  </color>
  <material>
   Полиэстер
  </material>
  <price>
   604376
  </price>
  <rating>
   3.28
  </rating>
  <reviews>
   300222
  </reviews>
  <new>
   +
  </new>
  <exclusive>
   yes
  </exclusive>
 </clothing>
 <clothing>
  <id>
   266801250
  </id>
  <name>
   Nike Umbrellas I-3082
  </name>
  <category>
   Umbrellas
  </category>
  <size>
   XXL
  </size>
  <color>
   Красный
  </color>
  <material>
   Хлопок
  </material>
  <price>
   242855
  </price>
  <rating>
   2.86
  </rating>
  <reviews>
   614603
  </reviews>
  <new>
   +
  </new>
  <sporty>
   no
  </sporty>
 </clothing>
 <clothing>
  <id>
   192640863
  </id>
  <name>
   Under Armour Socks X-1160
  </name>
  <category>
   Socks
  </category>
  <size>
   L
  </size>
  <color>
   Красный
  </color>
  <material>
   Хлопок
  </material>
  <price>
   490256
  </price>
  <rating>
   3.82
  </rating>
  <reviews>
   944919
  </reviews>
  <new>
   -
  </new>
  <exclusive>
   yes
  </exclusive>
 </clothing>
 <clothing>
  <id>
   446711086
  </id>
  <name>
   DC Gloves Q-5204
  </name>
  <category>
   Gloves
  </category>
  <size>
   M
  </size>
  <color>
   Красный
  </color>
  <material>
   Кожа
  </material>
  <price>
   926251
  </price>
  <rating>
   3.62
  </rating>
  <reviews>
   695898
  </reviews>
  <exclusive>
   no
  </exclusive>
  <sporty>
   yes
  </sporty>
 </clothing>
 <clothing>
  <id>
   163250982
  </id>
  <name>
   Fila Skirt Q-1883
  </name>
  <category>
   Skirt
  </category>
  <size>
   M
  </size>
  <color>
   Синий
  </color>
  <material>
   Кожа
  </material>
  <price>
   872632
  </price>
  <rating>
   4.11
  </rating>
  <reviews>
   639594
  </reviews>
  <new>
   -
  </new>
 </clothing>
 <clothing>
  <id>
   264879157
  </id>
  <name>
   Puma Jeans K-8828
  </name>
  <category>
   Jeans
  </category>
  <size>
   XL
  </size>
  <color>
   Фиолетовый
  </color>
  <material>
   Полиэстер
  </material>
  <price>
   364225
  </price>
  <rating>
   3.25
  </rating>
  <reviews>
   327738
  </reviews>
  <new>
   +
  </new>
  <exclusive>
   yes
  </exclusive>
  <sporty>
   yes
  </sporty>
 </clothing>
 <clothing>
  <id>
   558536901
  </id>
  <name>
   PleinSport Sweater L-4678
  </name>
  <category>
   Sweater
  </category>
  <size>
   S
  </size>
  <color>
   Желтый
  </color>
  <material>
   Полиэстер
  </material>
  <price>
   257312
  </price>
  <rating>
   1.61
  </rating>
  <reviews>
   269417
  </reviews>
  <new>
   +
  </new>
  <exclusive>
   yes
  </exclusive>
  <sporty>
   no
  </sporty>
 </clothing>
 <clothing>
  <id>
   989204139
  </id>
  <name>
   Under Armour Shoes B-1704
  </name>
  <category>
   Shoes
  </category>
  <size>
   M
  </size>
  <color>
   Желтый
  </color>
  <material>
   Полиэстер
  </material>
  <price>
   815248
  </price>
  <rating>
   3.55
  </rating>
  <reviews>
   55664
  </reviews>
  <exclusive>
   no
  </exclusive>
 </clothing>
 <clothing>
  <id>
   979539309
  </id>
  <name>
   Asics Shoes T-3429
  </name>
  <category>
   Shoes
  </category>
  <size>
   XXL
  </size>
  <color>
   Фиолетовый
  </color>
  <material>
   Лен
  </material>
  <price>
   316682
  </price>
  <rating>
   1.14
  </rating>
  <reviews>
   358768
  </reviews>
  <new>
   -
  </new>
  <exclusive>
   no
  </exclusive>
  <sporty>
   yes
  </sporty>
 </clothing>
 <clothing>
  <id>
   336657854
  </id>
  <name>
   Brooks Umbrellas S-6204
  </name>
  <category>
   Umbrellas
  </category>
  <size>
   S
  </size>
  <color>
   Голубой
  </color>
  <material>
   Полиэстер
  </material>
  <price>
   436358
  </price>
  <rating>
   2.63
  </rating>
  <reviews>
   276005
  </reviews>
  <new>
   -
  </new>
  <exclusive>
   yes
  </exclusive>
  <sporty>
   no
  </sporty>
 </clothing>
 <clothing>
  <id>
   104298470
  </id>
  <name>
   New Balance Sweater T-4199
  </name>
  <category>
   Sweater
  </category>
  <size>
   L
  </size>
  <color>
   Синий
  </color>
  <material>
   Нейлон
  </material>
  <price>
   920424
  </price>
  <rating>
   1.71
  </rating>
  <reviews>
   345487
  </reviews>
  <new>
   -
  </new>
  <exclusive>
   yes
  </exclusive>
  <sporty>
   yes
  </sporty>
 </clothing>
 <clothing>
  <id>
   879257557
  </id>
  <name>
   Lacoste Handbags R-3956
  </name>
  <category>
   Handbags
  </category>
  <size>
   XXL
  </size>
  <color>
   Зеленый
  </color>
  <material>
   Нейлон
  </material>
  <price>
   421525
  </price>
  <rating>
   1.58
  </rating>
  <reviews>
   493330
  </reviews>
  <new>
   -
  </new>
 </clothing>
 <clothing>
  <id>
   476208083
  </id>
  <name>
   Ellesse Skirt D-8278
  </name>
  <category>
   Skirt
  </category>
  <size>
   S
  </size>
  <color>
   Синий
  </color>
  <material>
   Хлопок
  </material>
  <price>
   582487
  </price>
  <rating>
   1.64
  </rating>
  <reviews>
   763000
  </reviews>
  <new>
   -
  </new>
  <sporty>
   yes
  </sporty>
 </clothing>
 <clothing>
  <id>
   882192794
  </id>
  <name>
   Under Armour Blouse B-4790
  </name>
  <category>
   Blouse
  </category>
  <size>
   XXL
  </size>
  <color>
   Голубой
  </color>
  <material>
   Хлопок
  </material>
  <price>
   372230
  </price>
  <rating>
   3.38
  </rating>
  <reviews>
   439338
  </reviews>
  <exclusive>
   no
  </exclusive>
  <sporty>
   no
  </sporty>
 </clothing>
 <clothing>
  <id>
   198250792
  </id>
  <name>
   Reebok Belts D-6023
  </name>
  <category>
   Belts
  </category>
  <size>
   M
  </size>
  <color>
   Оранжевый
  </color>
  <material>
   Нейлон
  </material>
  <price>
   142415
  </price>
  <rating>
   1.89
  </rating>
  <reviews>
   790740
  </reviews>
  <exclusive>
   yes
  </exclusive>
  <sporty>
   no
  </sporty>
 </clothing>
 <clothing>
  <id>
   780619984
  </id>
  <name>
   Adidas Hat L-6266
  </name>
  <category>
   Hat
  </category>
  <size>
   S
  </size>
  <color>
   Желтый
  </color>
  <material>
   Кожа
  </material>
  <price>
   169152
  </price>
  <rating>
   2.15
  </rating>
  <reviews>
   448522
  </reviews>
  <exclusive>
   yes
  </exclusive>
 </clothing>
 <clothing>
  <id>
   836483820
  </id>
  <name>
   Under Armour Jeans B-6867
  </name>
  <category>
   Jeans
  </category>
  <size>
   XL
  </size>
  <color>
   Фиолетовый
  </color>
  <material>
   Хлопок
  </material>
  <price>
   649718
  </price>
  <rating>
   2.05
  </rating>
  <reviews>
   866758
  </reviews>
 </clothing>
 <clothing>
  <id>
   599833717
  </id>
  <name>
   Converse T-shirt U-5560
  </name>
  <category>
   T-shirt
  </category>
  <size>
   L
  </size>
  <color>
   Фиолетовый
  </color>
  <material>
   Полиэстер
  </material>
  <price>
   449945
  </price>
  <rating>
   4.81
  </rating>
  <reviews>
   154370
  </reviews>
  <new>
   -
  </new>
  <sporty>
   yes
  </sporty>
 </clothing>
 <clothing>
  <id>
   118389826
  </id>
  <name>
   Vans Pants R-6594
  </name>
  <category>
   Pants
  </category>
  <size>
   XL
  </size>
  <color>
   Красный
  </color>
  <material>
   Лен
  </material>
  <price>
   646756
  </price>
  <rating>
   4.8
  </rating>
  <reviews>
   475460
  </reviews>
  <sporty>
   no
  </sporty>
 </clothing>
 <clothing>
  <id>
   880980343
  </id>
  <name>
   Fila Handbags E-8862
  </name>
  <category>
   Handbags
  </category>
  <size>
   XL
  </size>
  <color>
   Желтый
  </color>
  <material>
   Шерсть
  </material>
  <price>
   665419
  </price>
  <rating>
   4.3
  </rating>
  <reviews>
   547687
  </reviews>
  <new>
   -
  </new>
  <exclusive>
   no
  </exclusive>
 </clothing>
 <clothing>
  <id>
   226746549
  </id>
  <name>
   Reebok Skirt I-3508
  </name>
  <category>
   Skirt
  </category>
  <size>
   S
  </size>
  <color>
   Голубой
  </color>
  <material>
   Кожа
  </material>
  <price>
   675473
  </price>
  <rating>
   4.49
  </rating>
  <reviews>
   507879
  </reviews>
  <new>
   -
  </new>
  <sporty>
   yes
  </sporty>
 </clothing>
 <clothing>
  <id>
   554416274
  </id>
  <name>
   Lacoste Socks C-7927
  </name>
  <category>
   Socks
  </category>
  <size>
   S
  </size>
  <color>
   Зеленый
  </color>
  <material>
   Нейлон
  </material>
  <price>
   791320
  </price>
  <rating>
   3.07
  </rating>
  <reviews>
   120449
  </reviews>
 </clothing>
 <clothing>
  <id>
   461026589
  </id>
  <name>
   Under Armour Hat X-2905
  </name>
  <category>
   Hat
  </category>
  <size>
   L
  </size>
  <color>
   Зеленый
  </color>
  <material>
   Шелк
  </material>
  <price>
   342685
  </price>
  <rating>
   1.26
  </rating>
  <reviews>
   810609
  </reviews>
  <new>
   -
  </new>
 </clothing>
 <clothing>
  <id>
   373062156
  </id>
  <name>
   Vans Shoes A-9461
  </name>
  <category>
   Shoes
  </category>
  <size>
   XL
  </size>
  <color>
   Желтый
  </color>
  <material>
   Шерсть
  </material>
  <price>
   487202
  </price>
  <rating>
   2.35
  </rating>
  <reviews>
   953976
  </reviews>
  <exclusive>
   no
  </exclusive>
 </clothing>
 <clothing>
  <id>
   103240530
  </id>
  <name>
   Converse Hat C-2017
  </name>
  <category>
   Hat
  </category>
  <size>
   L
  </size>
  <color>
   Синий
  </color>
  <material>
   Шерсть
  </material>
  <price>
   992769
  </price>
  <rating>
   3.24
  </rating>
  <reviews>
   204748
  </reviews>
  <exclusive>
   no
  </exclusive>
 </clothing>
</clothing-items>
