<?xml version="1.0" encoding="utf-8"?>
<clothing-items>
 <clothing>
  <id>
   215112758
  </id>
  <name>
   Under Armour Sweater Z-9694
  </name>
  <category>
   Sweater
  </category>
  <size>
   L
  </size>
  <color>
   Зеленый
  </color>
  <material>
   Кожа
  </material>
  <price>
   229964
  </price>
  <rating>
   1.12
  </rating>
  <reviews>
   166771
  </reviews>
  <exclusive>
   no
  </exclusive>
 </clothing>
 <clothing>
  <id>
   575477335
  </id>
  <name>
   Converse Skirt P-2823
  </name>
  <category>
   Skirt
  </category>
  <size>
   XXL
  </size>
  <color>
   Оранжевый
  </color>
  <material>
   Вискоза
  </material>
  <price>
   391950
  </price>
  <rating>
   3.16
  </rating>
  <reviews>
   326556
  </reviews>
  <new>
   -
  </new>
  <exclusive>
   yes
  </exclusive>
  <sporty>
   yes
  </sporty>
 </clothing>
 <clothing>
  <id>
   563512185
  </id>
  <name>
   Asics Umbrellas Q-6796
  </name>
  <category>
   Umbrellas
  </category>
  <size>
   S
  </size>
  <color>
   Желтый
  </color>
  <material>
   Шелк
  </material>
  <price>
   805809
  </price>
  <rating>
   4.86
  </rating>
  <reviews>
   307653
  </reviews>
  <new>
   -
  </new>
  <sporty>
   no
  </sporty>
 </clothing>
 <clothing>
  <id>
   467067801
  </id>
  <name>
   DC Hat X-5239
  </name>
  <category>
   Hat
  </category>
  <size>
   XXL
  </size>
  <color>
   Голубой
  </color>
  <material>
   Шерсть
  </material>
  <price>
   446924
  </price>
  <rating>
   3.19
  </rating>
  <reviews>
   504171
  </reviews>
  <exclusive>
   no
  </exclusive>
  <sporty>
   yes
  </sporty>
 </clothing>
 <clothing>
  <id>
   904405488
  </id>
  <name>
   DC Gloves C-4760
  </name>
  <category>
   Gloves
  </category>
  <size>
   S
  </size>
  <color>
   Фиолетовый
  </color>
  <material>
   Кожа
  </material>
  <price>
   634339
  </price>
  <rating>
   4.47
  </rating>
  <reviews>
   243519
  </reviews>
  <new>
   -
  </new>
  <exclusive>
   no
  </exclusive>
 </clothing>
 <clothing>
  <id>
   853193171
  </id>
  <name>
   Addidas Handbags B-6319
  </name>
  <category>
   Handbags
  </category>
  <size>
   M
  </size>
  <color>
   Синий
  </color>
  <material>
   Кожа
  </material>
  <price>
   228137
  </price>
  <rating>
   2.61
  </rating>
  <reviews>
   255616
  </reviews>
  <new>
   -
  </new>
 </clothing>
 <clothing>
  <id>
   220342791
  </id>
  <name>
   Under Armour Jeans I-6455
  </name>
  <category>
   Jeans
  </category>
  <size>
   XL
  </size>
  <color>
   Красный
  </color>
  <material>
   Кожа
  </material>
  <price>
   828915
  </price>
  <rating>
   1.67
  </rating>
  <reviews>
   279898
  </reviews>
  <sporty>
   yes
  </sporty>
 </clothing>
 <clothing>
  <id>
   689555864
  </id>
  <name>
   Brooks T-shirt J-7760
  </name>
  <category>
   T-shirt
  </category>
  <size>
   S
  </size>
  <color>
   Фиолетовый
  </color>
  <material>
   Шерсть
  </material>
  <price>
   445797
  </price>
  <rating>
   4.29
  </rating>
  <reviews>
   388676
  </reviews>
  <new>
   -
  </new>
  <sporty>
   no
  </sporty>
 </clothing>
 <clothing>
  <id>
   818771969
  </id>
  <name>
   New Balance Socks J-1705
  </name>
  <category>
   Socks
  </category>
  <size>
   L
  </size>
  <color>
   Голубой
  </color>
  <material>
   Нейлон
  </material>
  <price>
   734273
  </price>
  <rating>
   2.46
  </rating>
  <reviews>
   620466
  </reviews>
 </clothing>
 <clothing>
  <id>
   765276866
  </id>
  <name>
   Lacoste Socks A-3092
  </name>
  <category>
   Socks
  </category>
  <size>
   XL
  </size>
  <color>
   Фиолетовый
  </color>
  <material>
   Полиэстер
  </material>
  <price>
   543948
  </price>
  <rating>
   1.54
  </rating>
  <reviews>
   75819
  </reviews>
  <new>
   +
  </new>
  <exclusive>
   no
  </exclusive>
  <sporty>
   yes
  </sporty>
 </clothing>
 <clothing>
  <id>
   347575575
  </id>
  <name>
   Ellesse Handbags K-5229
  </name>
  <category>
   Handbags
  </category>
  <size>
   L
  </size>
  <color>
   Синий
  </color>
  <material>
   Вискоза
  </material>
  <price>
   593878
  </price>
  <rating>
   2.61
  </rating>
  <reviews>
   932276
  </reviews>
  <new>
   +
  </new>
 </clothing>
 <clothing>
  <id>
   326943165
  </id>
  <name>
   Asics Handbags U-7828
  </name>
  <category>
   Handbags
  </category>
  <size>
   L
  </size>
  <color>
   Синий
  </color>
  <material>
   Нейлон
  </material>
  <price>
   709588
  </price>
  <rating>
   4.44
  </rating>
  <reviews>
   118905
  </reviews>
  <new>
   -
  </new>
  <sporty>
   yes
  </sporty>
 </clothing>
 <clothing>
  <id>
   897885059
  </id>
  <name>
   Nike Shoes X-6045
  </name>
  <category>
   Shoes
  </category>
  <size>
   L
  </size>
  <color>
   Красный
  </color>
  <material>
   Хлопок
  </material>
  <price>
   255499
  </price>
  <rating>
   2.39
  </rating>
  <reviews>
   397886
  </reviews>
  <new>
   -
  </new>
  <sporty>
   no
  </sporty>
 </clothing>
 <clothing>
  <id>
   844530631
  </id>
  <name>
   Brooks Dress P-9697
  </name>
  <category>
   Dress
  </category>
  <size>
   XXL
  </size>
  <color>
   Желтый
  </color>
  <material>
   Кожа
  </material>
  <price>
   375700
  </price>
  <rating>
   1.21
  </rating>
  <reviews>
   532780
  </reviews>
  <new>
   +
  </new>
  <exclusive>
   no
  </exclusive>
  <sporty>
   yes
  </sporty>
 </clothing>
 <clothing>
  <id>
   623845109
  </id>
  <name>
   PleinSport Shirt N-9731
  </name>
  <category>
   Shirt
  </category>
  <size>
   XXL
  </size>
  <color>
   Голубой
  </color>
  <material>
   Полиэстер
  </material>
  <price>
   760273
  </price>
  <rating>
   2.14
  </rating>
  <reviews>
   124305
  </reviews>
  <sporty>
   no
  </sporty>
 </clothing>
 <clothing>
  <id>
   608163988
  </id>
  <name>
   DC Skirt D-3962
  </name>
  <category>
   Skirt
  </category>
  <size>
   S
  </size>
  <color>
   Фиолетовый
  </color>
  <material>
   Вискоза
  </material>
  <price>
   711520
  </price>
  <rating>
   3.46
  </rating>
  <reviews>
   153149
  </reviews>
  <exclusive>
   yes
  </exclusive>
  <sporty>
   no
  </sporty>
 </clothing>
 <clothing>
  <id>
   471400657
  </id>
  <name>
   Ellesse Handbags S-2453
  </name>
  <category>
   Handbags
  </category>
  <size>
   XXL
  </size>
  <color>
   Голубой
  </color>
  <material>
   Вискоза
  </material>
  <price>
   444867
  </price>
  <rating>
   1.33
  </rating>
  <reviews>
   858209
  </reviews>
  <new>
   -
  </new>
  <exclusive>
   no
  </exclusive>
 </clothing>
 <clothing>
  <id>
   214328484
  </id>
  <name>
   Fila Skirt X-4289
  </name>
  <category>
   Skirt
  </category>
  <size>
   M
  </size>
  <color>
   Красный
  </color>
  <material>
   Полиэстер
  </material>
  <price>
   868205
  </price>
  <rating>
   3.12
  </rating>
  <reviews>
   453259
  </reviews>
  <new>
   +
  </new>
 </clothing>
 <clothing>
  <id>
   321233388
  </id>
  <name>
   Converse T-shirt C-7136
  </name>
  <category>
   T-shirt
  </category>
  <size>
   M
  </size>
  <color>
   Фиолетовый
  </color>
  <material>
   Хлопок
  </material>
  <price>
   226709
  </price>
  <rating>
   2.9
  </rating>
  <reviews>
   15634
  </reviews>
 </clothing>
 <clothing>
  <id>
   197783834
  </id>
  <name>
   Vans Hat U-8358
  </name>
  <category>
   Hat
  </category>
  <size>
   XL
  </size>
  <color>
   Голубой
  </color>
  <material>
   Вискоза
  </material>
  <price>
   579950
  </price>
  <rating>
   1.4
  </rating>
  <reviews>
   716934
  </reviews>
  <new>
   -
  </new>
  <sporty>
   yes
  </sporty>
 </clothing>
 <clothing>
  <id>
   945967455
  </id>
  <name>
   Lacoste Blouse Y-5234
  </name>
  <category>
   Blouse
  </category>
  <size>
   XXL
  </size>
  <color>
   Оранжевый
  </color>
  <material>
   Хлопок
  </material>
  <price>
   885150
  </price>
  <rating>
   1.13
  </rating>
  <reviews>
   306085
  </reviews>
  <new>
   -
  </new>
 </clothing>
 <clothing>
  <id>
   336345634
  </id>
  <name>
   Brooks Shirt N-5468
  </name>
  <category>
   Shirt
  </category>
  <size>
   S
  </size>
  <color>
   Красный
  </color>
  <material>
   Шерсть
  </material>
  <price>
   725529
  </price>
  <rating>
   1.44
  </rating>
  <reviews>
   877089
  </reviews>
  <new>
   +
  </new>
  <exclusive>
   yes
  </exclusive>
  <sporty>
   no
  </sporty>
 </clothing>
 <clothing>
  <id>
   674083018
  </id>
  <name>
   Fila Shoes W-3030
  </name>
  <category>
   Shoes
  </category>
  <size>
   M
  </size>
  <color>
   Голубой
  </color>
  <material>
   Хлопок
  </material>
  <price>
   426959
  </price>
  <rating>
   2.15
  </rating>
  <reviews>
   596753
  </reviews>
  <new>
   +
  </new>
  <exclusive>
   no
  </exclusive>
  <sporty>
   yes
  </sporty>
 </clothing>
 <clothing>
  <id>
   852158239
  </id>
  <name>
   PleinSport Hat B-7619
  </name>
  <category>
   Hat
  </category>
  <size>
   XL
  </size>
  <color>
   Оранжевый
  </color>
  <material>
   Нейлон
  </material>
  <price>
   564087
  </price>
  <rating>
   2.01
  </rating>
  <reviews>
   846106
  </reviews>
  <exclusive>
   yes
  </exclusive>
 </clothing>
 <clothing>
  <id>
   420800050
  </id>
  <name>
   Puma Socks R-8919
  </name>
  <category>
   Socks
  </category>
  <size>
   XL
  </size>
  <color>
   Зеленый
  </color>
  <material>
   Лен
  </material>
  <price>
   353648
  </price>
  <rating>
   3.69
  </rating>
  <reviews>
   567439
  </reviews>
  <new>
   +
  </new>
  <exclusive>
   no
  </exclusive>
  <sporty>
   no
  </sporty>
 </clothing>
 <clothing>
  <id>
   731298361
  </id>
  <name>
   Nike Gloves N-5784
  </name>
  <category>
   Gloves
  </category>
  <size>
   L
  </size>
  <color>
   Желтый
  </color>
  <material>
   Хлопок
  </material>
  <price>
   404748
  </price>
  <rating>
   3.08
  </rating>
  <reviews>
   916511
  </reviews>
  <exclusive>
   no
  </exclusive>
  <sporty>
   yes
  </sporty>
 </clothing>
 <clothing>
  <id>
   396830326
  </id>
  <name>
   Puma Jacket Q-3494
  </name>
  <category>
   Jacket
  </category>
  <size>
   M
  </size>
  <color>
   Зеленый
  </color>
  <material>
   Лен
  </material>
  <price>
   805105
  </price>
  <rating>
   2.96
  </rating>
  <reviews>
   552864
  </reviews>
  <new>
   +
  </new>
  <exclusive>
   yes
  </exclusive>
 </clothing>
 <clothing>
  <id>
   961323087
  </id>
  <name>
   Vans Skirt I-6937
  </name>
  <category>
   Skirt
  </category>
  <size>
   XL
  </size>
  <color>
   Фиолетовый
  </color>
  <material>
   Лен
  </material>
  <price>
   282112
  </price>
  <rating>
   3.79
  </rating>
  <reviews>
   307328
  </reviews>
  <new>
   -
  </new>
 </clothing>
 <clothing>
  <id>
   473543241
  </id>
  <name>
   Asics Jeans R-2791
  </name>
  <category>
   Jeans
  </category>
  <size>
   S
  </size>
  <color>
   Фиолетовый
  </color>
  <material>
   Шелк
  </material>
  <price>
   946390
  </price>
  <rating>
   1.89
  </rating>
  <reviews>
   330684
  </reviews>
  <new>
   -
  </new>
  <sporty>
   yes
  </sporty>
 </clothing>
 <clothing>
  <id>
   659747031
  </id>
  <name>
   New Balance Shirt U-2702
  </name>
  <category>
   Shirt
  </category>
  <size>
   M
  </size>
  <color>
   Зеленый
  </color>
  <material>
   Вискоза
  </material>
  <price>
   102039
  </price>
  <rating>
   3.23
  </rating>
  <reviews>
   249004
  </reviews>
  <new>
   +
  </new>
  <sporty>
   yes
  </sporty>
 </clothing>
 <clothing>
  <id>
   405868489
  </id>
  <name>
   Under Armour Dress R-8279
  </name>
  <category>
   Dress
  </category>
  <size>
   XL
  </size>
  <color>
   Синий
  </color>
  <material>
   Шерсть
  </material>
  <price>
   969001
  </price>
  <rating>
   3.04
  </rating>
  <reviews>
   269257
  </reviews>
  <exclusive>
   no
  </exclusive>
  <sporty>
   no
  </sporty>
 </clothing>
</clothing-items>
